pyd_test_package/__init__.py
pyd_test_package/clc_component.py
pyd_test_package/hello_world.py
pyd_test_package-0.0.2.dist-info/LICENSE
pyd_test_package-0.0.2.dist-info/METADATA
pyd_test_package-0.0.2.dist-info/WHEEL
pyd_test_package-0.0.2.dist-info/top_level.txt
pyd_test_package-0.0.2.dist-info/RECORD
