Metadata-Version: 2.1
Name: pyd-test-package
Version: 0.0.2
Summary: package test
Author: pyd
Author-email: panydacademy@163.com
License: UNKNOWN
Platform: UNKNOWN
Requires-Python: >=3.6
License-File: LICENSE
